auto_doc_collector/__init__.py
auto_doc_collector/asgi.py
auto_doc_collector/settings.py
auto_doc_collector/urls.py
auto_doc_collector/wsgi.py
core/__init__.py
core/admin.py
core/apps.py
core/models.py
core/tests.py
core/views.py
core/migrations/__init__.py
db_to_excel-0.1.dist-info/LICENSE
db_to_excel-0.1.dist-info/METADATA
db_to_excel-0.1.dist-info/WHEEL
db_to_excel-0.1.dist-info/entry_points.txt
db_to_excel-0.1.dist-info/top_level.txt
db_to_excel-0.1.dist-info/RECORD
